mecsimcalc/__init__.py
mecsimcalc/plot_draw.py
mecsimcalc/file_utils/__init__.py
mecsimcalc/file_utils/general_utils.py
mecsimcalc/file_utils/image_utils.py
mecsimcalc/file_utils/plotting_utils.py
mecsimcalc/file_utils/quiz_utils.py
mecsimcalc/file_utils/spreadsheet_utils.py
mecsimcalc/file_utils/table_utils.py
mecsimcalc/file_utils/text_utils.py
mecsimcalc-0.2.1.dist-info/LICENSE
mecsimcalc-0.2.1.dist-info/METADATA
mecsimcalc-0.2.1.dist-info/WHEEL
mecsimcalc-0.2.1.dist-info/top_level.txt
mecsimcalc-0.2.1.dist-info/RECORD
