Metadata-Version: 2.1
Name: mecsimcalc
Version: 0.2.1
Summary: Useful functions for MecSimCalc.com
Author: MecSimCalc
Author-email: <info@mecsimcalc.com>
Keywords: python,MecSimCalc,Calculator,Simple
Classifier: Development Status :: 5 - Production/Stable
Classifier: Intended Audience :: Developers
Classifier: Programming Language :: Python :: 3.6
Classifier: Programming Language :: Python :: 3.7
Classifier: Programming Language :: Python :: 3.8
Classifier: Programming Language :: Python :: 3.9
Classifier: Programming Language :: Python :: 3.10
Classifier: Programming Language :: Python :: 3.11
Classifier: Programming Language :: Python :: 3.12
Classifier: Operating System :: Unix
Classifier: Operating System :: MacOS :: MacOS X
Classifier: Operating System :: Microsoft :: Windows
License-File: LICENSE
Requires-Dist: Pillow
Requires-Dist: pandas
Requires-Dist: matplotlib
Requires-Dist: openpyxl
Requires-Dist: PyJWT
Requires-Dist: cryptography
Requires-Dist: requests
Requires-Dist: plotly
Provides-Extra: dev
Requires-Dist: pytest >=7.0 ; extra == 'dev'
Requires-Dist: twine >=4.0.2 ; extra == 'dev'
